ecell4/__init__.py
ecell4/prelude.py
ecell4/datasource/__init__.py
ecell4/datasource/biocyc.py
ecell4/datasource/biogrid.py
ecell4/datasource/ecocyc.py
ecell4/datasource/pdb.py
ecell4/datasource/psicquic.py
ecell4/datasource/pubmed.py
ecell4/datasource/rdf.py
ecell4/datasource/sbml.py
ecell4/datasource/sparql.py
ecell4/datasource/string.py
ecell4/datasource/uniprot.py
ecell4/extra/__init__.py
ecell4/extra/_pysb.py
ecell4/extra/_unit.py
ecell4/extra/azure_batch.py
ecell4/extra/bdml.py
ecell4/extra/ensemble.py
ecell4/extra/latex.py
ecell4/extra/sge.py
ecell4/extra/slurm.py
ecell4/extra/unit.py
ecell4/extra/unit_checker.py
ecell4/extra/vtkview.py
ecell4/mca/__init__.py
ecell4/mca/cc.py
ecell4/mca/network.py
ecell4/plotting/__init__.py
ecell4/plotting/_core.py
ecell4/plotting/_elegans.py
ecell4/plotting/_matplotlib.py
ecell4/plotting/_plotly.py
ecell4/plotting/styles.py
ecell4/util/__init__.py
ecell4/util/cyjs.py
ecell4/util/decorator.py
ecell4/util/decorator_base.py
ecell4/util/logger.py
ecell4/util/model_parser.py
ecell4/util/parseobj.py
ecell4/util/ports.py
ecell4/util/progressbar.py
ecell4/util/session.py
ecell4/util/show.py
ecell4/util/simulation.py
ecell4/util/viz.py
ecell4/util/templates/init_cyjs.js
ecell4/util/templates/movie.tmpl
ecell4/util/templates/nya.tmpl
ecell4/util/templates/particles.tmpl
ecell4/util/templates/template.html
ecell4/util/templates/ecelllogo/logo01.png
ecell4/util/templates/ecelllogo/logo02.png
ecell4/util/templates/ecelllogo/logo03.png
ecell4/util/templates/ecelllogo/logo04.png
ecell4/util/templates/ecelllogo/logo05.png
ecell4/util/templates/ecelllogo/logo06.png
ecell4/util/templates/ecelllogo/logo07.png
ecell4/util/templates/ecelllogo/logo08.png
ecell4/util/templates/ecelllogo/logo09.png
ecell4/util/templates/ecelllogo/logo10.png
ecell4/util/templates/ecelllogo/logo11.png
ecell4/util/templates/ecelllogo/logo12.png
ecell4/util/templates/ecelllogo/logo13.png
ecell4/util/templates/ecelllogo/logo14.png
ecell4-1.2.1.dist-info/LICENSE
ecell4-1.2.1.dist-info/METADATA
ecell4-1.2.1.dist-info/WHEEL
ecell4-1.2.1.dist-info/top_level.txt
ecell4-1.2.1.dist-info/RECORD
